<?xml version="1.0" encoding="utf-8"?>
<extension version="1.6.0" type="plugin" group="system" method="upgrade">
    <name>Installer</name>
	<author>RocketTheme, LLC</author>
	<creationDate>November 4, 2015</creationDate>
	<copyright>(C) 2005 - 2015 RocketTheme, LLC. All rights reserved.</copyright>
	<license>http://www.gnu.org/copyleft/gpl.html GNU/GPL</license>
	<authorEmail>support@rockettheme.com</authorEmail>
	<authorUrl>http://www.rockettheme.com</authorUrl>
	<version>1.5</version>
	<description>Quasar Template v1.5</description>
    <scriptfile>install.script.php</scriptfile>
    <files>
        <filename plugin="rt_quasar_installer">installer.php</filename>
    </files>
    <cogs>
        <cog type="template" client="site" access="1" enabled="true" protected="false" remove_style="true">
            rt_quasar
            <name>Quasar Template</name>
            <description>Parent for all PHP based projects</description>
            <style name="Quasar - Default" default="false" master="true" paramsfile="template-options.xml"/>
        </cog>
    </cogs>
</extension>
